pycounts_je/__init__.py
pycounts_je/plotting.py
pycounts_je/pycounts_je.py
pycounts_je-0.1.0.dist-info/LICENSE
pycounts_je-0.1.0.dist-info/METADATA
pycounts_je-0.1.0.dist-info/WHEEL
pycounts_je-0.1.0.dist-info/RECORD
